[
  {
    "name": "В личном кабинете добавлен новый способ вывода денег на карты Visa и MasterCard",
    "url": "/1.pdf"
  },
  {
    "name": "В личном кабинете добавлен новый способ вывода денег на карты Visa и MasterCard",
    "url": "/1.pdf"
  },
  {
    "name": "В личном кабинете добавлен новый способ вывода денег на карты Visa и MasterCard",
    "url": "/1.pdf"
  },
  {
    "name": "В личном кабинете добавлен новый способ вывода денег на карты Visa и MasterCard",
    "url": "/1.pdf"
  },
  {
    "name": "В личном кабинете добавлен новый способ вывода денег на карты Visa и MasterCard",
    "url": "/1.pdf"
  },
  {
    "name": "В личном кабинете добавлен новый способ вывода денег на карты Visa и MasterCard",
    "url": "/1.pdf"
  },
  {
    "name": "В личном кабинете добавлен новый способ вывода денег на карты Visa и MasterCard",
    "url": "/1.pdf"
  }
]